jsoni18n/__init__.py
jsoni18n/languages.py
jsoni18n/messages.py
jsoni18n-1.0.0.dist-info/LICENSE
jsoni18n-1.0.0.dist-info/METADATA
jsoni18n-1.0.0.dist-info/WHEEL
jsoni18n-1.0.0.dist-info/top_level.txt
jsoni18n-1.0.0.dist-info/RECORD
