Metadata-Version: 2.1
Name: jsoni18n
Version: 1.0.0
Summary: A simple i18n system using json + pycountry alpha_3 ISO codes.
Home-page: https://github.com/Pycryptor10/py-jsoni18n
Author: Pycryptor10
Author-email: Pycryptor10@gmail.com
Maintainer: Pycryptor10
Maintainer-email: Pycryptor10@gmail.com
License: GPL3
Keywords: pycountry localization json i18n l10n internationalization
Platform: any
Classifier: Development Status :: 5 - Production/Stable
Classifier: Intended Audience :: Developers
Classifier: License :: OSI Approved :: GNU General Public License v3 (GPLv3)
Classifier: Operating System :: POSIX :: Linux
Classifier: Operating System :: Microsoft :: Windows
Classifier: Operating System :: MacOS
Classifier: Programming Language :: Python
Classifier: Programming Language :: Python :: 3
Classifier: Programming Language :: Python :: 3 :: Only
Classifier: Programming Language :: Python :: 3.8
Classifier: Programming Language :: Python :: 3.9
Classifier: Programming Language :: Python :: 3.10
Classifier: Topic :: Software Development
Classifier: Topic :: Software Development :: Libraries
Classifier: Topic :: Software Development :: Localization
Requires-Python: >=3.8
License-File: LICENSE
Requires-Dist: pycountry (==20.7.3)
